rireki/__init__.py
rireki/cli.py
rireki/commands/__init__.py
rireki/commands/add.py
rireki/commands/add_test.py
rireki/commands/backup.py
rireki/commands/backup_test.py
rireki/commands/clean.py
rireki/commands/clean_test.py
rireki/commands/status.py
rireki/commands/status_test.py
rireki/core/__init__.py
rireki/core/backup.py
rireki/core/config.py
rireki/core/configurable.py
rireki/core/driver.py
rireki/core/project.py
rireki/core/projects_manager.py
rireki/core/retention_policy.py
rireki/core/store.py
rireki/drivers/__init__.py
rireki/drivers/custom.py
rireki/drivers/custom_test.py
rireki/drivers/files.py
rireki/drivers/files_test.py
rireki/drivers/index.py
rireki/stores/__init__.py
rireki/stores/aws.py
rireki/stores/digital_ocean.py
rireki/stores/digital_ocean_test.py
rireki/stores/index.py
rireki/stores/local.py
rireki/utils/__init__.py
rireki/utils/array_helpers.py
rireki/utils/file_helpers.py
rireki/utils/log_helpers.py
rireki/utils/output.py
rireki/utils/output_test.py
rireki/utils/string_helpers.py
rireki/utils/string_helpers_test.py
rireki/utils/time_helpers.py
rireki-0.1.3.dist-info/LICENSE
rireki-0.1.3.dist-info/METADATA
rireki-0.1.3.dist-info/WHEEL
rireki-0.1.3.dist-info/entry_points.txt
rireki-0.1.3.dist-info/top_level.txt
rireki-0.1.3.dist-info/RECORD
