Metadata-Version: 2.1
Name: rireki
Version: 0.1.3
Summary: CLI backup tool.
Home-page: https://github.com/noeldemartin/rireki
Author: Noel De Martin
Author-email: noeldemartin@gmail.com
License: MIT
Platform: UNKNOWN
License-File: LICENSE
Requires-Dist: boto3
Requires-Dist: click
Requires-Dist: toml
